{
    "directed": false,
    "multigraph": false,
    "graph": {},
    "nodes": [
        {
            "id": 1
        },
        {
            "id": 427
        },
        {
            "id": 366
        },
        {
            "id": 3
        },
        {
            "id": 61
        },
        {
            "id": 112
        },
        {
            "id": 6
        },
        {
            "id": 99
        },
        {
            "id": 251
        },
        {
            "id": 7
        },
        {
            "id": 177
        },
        {
            "id": 451
        },
        {
            "id": 8
        },
        {
            "id": 27
        },
        {
            "id": 17
        },
        {
            "id": 9
        },
        {
            "id": 62
        },
        {
            "id": 174
        },
        {
            "id": 10
        },
        {
            "id": 343
        },
        {
            "id": 426
        },
        {
            "id": 14
        },
        {
            "id": 474
        },
        {
            "id": 364
        },
        {
            "id": 15
        },
        {
            "id": 4
        },
        {
            "id": 206
        },
        {
            "id": 428
        },
        {
            "id": 313
        },
        {
            "id": 18
        },
        {
            "id": 348
        },
        {
            "id": 106
        },
        {
            "id": 20
        },
        {
            "id": 184
        },
        {
            "id": 356
        },
        {
            "id": 25
        },
        {
            "id": 303
        },
        {
            "id": 95
        },
        {
            "id": 78
        },
        {
            "id": 0
        },
        {
            "id": 32
        },
        {
            "id": 86
        },
        {
            "id": 228
        },
        {
            "id": 33
        },
        {
            "id": 479
        },
        {
            "id": 108
        },
        {
            "id": 35
        },
        {
            "id": 170
        },
        {
            "id": 368
        },
        {
            "id": 41
        },
        {
            "id": 404
        },
        {
            "id": 444
        },
        {
            "id": 43
        },
        {
            "id": 146
        },
        {
            "id": 136
        },
        {
            "id": 45
        },
        {
            "id": 29
        },
        {
            "id": 334
        },
        {
            "id": 46
        },
        {
            "id": 40
        },
        {
            "id": 85
        },
        {
            "id": 49
        },
        {
            "id": 124
        },
        {
            "id": 227
        },
        {
            "id": 50
        },
        {
            "id": 221
        },
        {
            "id": 278
        },
        {
            "id": 52
        },
        {
            "id": 392
        },
        {
            "id": 211
        },
        {
            "id": 53
        },
        {
            "id": 247
        },
        {
            "id": 266
        },
        {
            "id": 59
        },
        {
            "id": 180
        },
        {
            "id": 126
        },
        {
            "id": 66
        },
        {
            "id": 147
        },
        {
            "id": 214
        },
        {
            "id": 63
        },
        {
            "id": 67
        },
        {
            "id": 463
        },
        {
            "id": 64
        },
        {
            "id": 120
        },
        {
            "id": 229
        },
        {
            "id": 65
        },
        {
            "id": 80
        },
        {
            "id": 467
        },
        {
            "id": 248
        },
        {
            "id": 68
        },
        {
            "id": 432
        },
        {
            "id": 187
        },
        {
            "id": 69
        },
        {
            "id": 230
        },
        {
            "id": 30
        },
        {
            "id": 70
        },
        {
            "id": 231
        },
        {
            "id": 387
        },
        {
            "id": 72
        },
        {
            "id": 207
        },
        {
            "id": 418
        },
        {
            "id": 76
        },
        {
            "id": 298
        },
        {
            "id": 269
        },
        {
            "id": 316
        },
        {
            "id": 381
        },
        {
            "id": 82
        },
        {
            "id": 138
        },
        {
            "id": 384
        },
        {
            "id": 84
        },
        {
            "id": 152
        },
        {
            "id": 105
        },
        {
            "id": 87
        },
        {
            "id": 117
        },
        {
            "id": 101
        },
        {
            "id": 91
        },
        {
            "id": 197
        },
        {
            "id": 149
        },
        {
            "id": 92
        },
        {
            "id": 38
        },
        {
            "id": 357
        },
        {
            "id": 93
        },
        {
            "id": 416
        },
        {
            "id": 233
        },
        {
            "id": 94
        },
        {
            "id": 181
        },
        {
            "id": 407
        },
        {
            "id": 96
        },
        {
            "id": 73
        },
        {
            "id": 166
        },
        {
            "id": 100
        },
        {
            "id": 478
        },
        {
            "id": 264
        },
        {
            "id": 89
        },
        {
            "id": 388
        },
        {
            "id": 103
        },
        {
            "id": 252
        },
        {
            "id": 119
        },
        {
            "id": 104
        },
        {
            "id": 200
        },
        {
            "id": 107
        },
        {
            "id": 287
        },
        {
            "id": 236
        },
        {
            "id": 71
        },
        {
            "id": 273
        },
        {
            "id": 109
        },
        {
            "id": 54
        },
        {
            "id": 137
        },
        {
            "id": 110
        },
        {
            "id": 319
        },
        {
            "id": 28
        },
        {
            "id": 57
        },
        {
            "id": 176
        },
        {
            "id": 113
        },
        {
            "id": 190
        },
        {
            "id": 114
        },
        {
            "id": 58
        },
        {
            "id": 347
        },
        {
            "id": 115
        },
        {
            "id": 239
        },
        {
            "id": 335
        },
        {
            "id": 116
        },
        {
            "id": 456
        },
        {
            "id": 345
        },
        {
            "id": 118
        },
        {
            "id": 447
        },
        {
            "id": 260
        },
        {
            "id": 466
        },
        {
            "id": 241
        },
        {
            "id": 293
        },
        {
            "id": 433
        },
        {
            "id": 127
        },
        {
            "id": 163
        },
        {
            "id": 412
        },
        {
            "id": 130
        },
        {
            "id": 139
        },
        {
            "id": 168
        },
        {
            "id": 133
        },
        {
            "id": 134
        },
        {
            "id": 36
        },
        {
            "id": 135
        },
        {
            "id": 256
        },
        {
            "id": 182
        },
        {
            "id": 457
        },
        {
            "id": 140
        },
        {
            "id": 90
        },
        {
            "id": 337
        },
        {
            "id": 143
        },
        {
            "id": 31
        },
        {
            "id": 144
        },
        {
            "id": 210
        },
        {
            "id": 88
        },
        {
            "id": 390
        },
        {
            "id": 422
        },
        {
            "id": 271
        },
        {
            "id": 350
        },
        {
            "id": 151
        },
        {
            "id": 131
        },
        {
            "id": 162
        },
        {
            "id": 155
        },
        {
            "id": 378
        },
        {
            "id": 299
        },
        {
            "id": 156
        },
        {
            "id": 83
        },
        {
            "id": 159
        },
        {
            "id": 148
        },
        {
            "id": 369
        },
        {
            "id": 160
        },
        {
            "id": 111
        },
        {
            "id": 205
        },
        {
            "id": 161
        },
        {
            "id": 51
        },
        {
            "id": 411
        },
        {
            "id": 389
        },
        {
            "id": 167
        },
        {
            "id": 253
        },
        {
            "id": 314
        },
        {
            "id": 377
        },
        {
            "id": 171
        },
        {
            "id": 202
        },
        {
            "id": 142
        },
        {
            "id": 173
        },
        {
            "id": 409
        },
        {
            "id": 178
        },
        {
            "id": 405
        },
        {
            "id": 185
        },
        {
            "id": 179
        },
        {
            "id": 458
        },
        {
            "id": 315
        },
        {
            "id": 175
        },
        {
            "id": 399
        },
        {
            "id": 183
        },
        {
            "id": 258
        },
        {
            "id": 24
        },
        {
            "id": 439
        },
        {
            "id": 44
        },
        {
            "id": 398
        },
        {
            "id": 188
        },
        {
            "id": 446
        },
        {
            "id": 437
        },
        {
            "id": 164
        },
        {
            "id": 217
        },
        {
            "id": 191
        },
        {
            "id": 464
        },
        {
            "id": 192
        },
        {
            "id": 281
        },
        {
            "id": 194
        },
        {
            "id": 391
        },
        {
            "id": 359
        },
        {
            "id": 195
        },
        {
            "id": 459
        },
        {
            "id": 329
        },
        {
            "id": 196
        },
        {
            "id": 272
        },
        {
            "id": 280
        },
        {
            "id": 265
        },
        {
            "id": 470
        },
        {
            "id": 276
        },
        {
            "id": 324
        },
        {
            "id": 396
        },
        {
            "id": 232
        },
        {
            "id": 212
        },
        {
            "id": 270
        },
        {
            "id": 477
        },
        {
            "id": 213
        },
        {
            "id": 23
        },
        {
            "id": 277
        },
        {
            "id": 215
        },
        {
            "id": 234
        },
        {
            "id": 421
        },
        {
            "id": 354
        },
        {
            "id": 218
        },
        {
            "id": 397
        },
        {
            "id": 219
        },
        {
            "id": 201
        },
        {
            "id": 243
        },
        {
            "id": 223
        },
        {
            "id": 141
        },
        {
            "id": 328
        },
        {
            "id": 224
        },
        {
            "id": 60
        },
        {
            "id": 327
        },
        {
            "id": 145
        },
        {
            "id": 332
        },
        {
            "id": 317
        },
        {
            "id": 462
        },
        {
            "id": 431
        },
        {
            "id": 267
        },
        {
            "id": 413
        },
        {
            "id": 5
        },
        {
            "id": 290
        },
        {
            "id": 352
        },
        {
            "id": 300
        },
        {
            "id": 235
        },
        {
            "id": 26
        },
        {
            "id": 448
        },
        {
            "id": 237
        },
        {
            "id": 325
        },
        {
            "id": 307
        },
        {
            "id": 238
        },
        {
            "id": 471
        },
        {
            "id": 361
        },
        {
            "id": 16
        },
        {
            "id": 222
        },
        {
            "id": 240
        },
        {
            "id": 395
        },
        {
            "id": 430
        },
        {
            "id": 245
        },
        {
            "id": 172
        },
        {
            "id": 2
        },
        {
            "id": 189
        },
        {
            "id": 150
        },
        {
            "id": 440
        },
        {
            "id": 363
        },
        {
            "id": 254
        },
        {
            "id": 154
        },
        {
            "id": 312
        },
        {
            "id": 262
        },
        {
            "id": 294
        },
        {
            "id": 263
        },
        {
            "id": 362
        },
        {
            "id": 128
        },
        {
            "id": 473
        },
        {
            "id": 268
        },
        {
            "id": 434
        },
        {
            "id": 340
        },
        {
            "id": 198
        },
        {
            "id": 274
        },
        {
            "id": 331
        },
        {
            "id": 275
        },
        {
            "id": 98
        },
        {
            "id": 34
        },
        {
            "id": 12
        },
        {
            "id": 401
        },
        {
            "id": 374
        },
        {
            "id": 306
        },
        {
            "id": 286
        },
        {
            "id": 282
        },
        {
            "id": 284
        },
        {
            "id": 285
        },
        {
            "id": 429
        },
        {
            "id": 472
        },
        {
            "id": 288
        },
        {
            "id": 375
        },
        {
            "id": 400
        },
        {
            "id": 220
        },
        {
            "id": 438
        },
        {
            "id": 333
        },
        {
            "id": 226
        },
        {
            "id": 338
        },
        {
            "id": 309
        },
        {
            "id": 385
        },
        {
            "id": 301
        },
        {
            "id": 330
        },
        {
            "id": 302
        },
        {
            "id": 323
        },
        {
            "id": 420
        },
        {
            "id": 304
        },
        {
            "id": 344
        },
        {
            "id": 305
        },
        {
            "id": 55
        },
        {
            "id": 353
        },
        {
            "id": 443
        },
        {
            "id": 310
        },
        {
            "id": 246
        },
        {
            "id": 250
        },
        {
            "id": 476
        },
        {
            "id": 449
        },
        {
            "id": 203
        },
        {
            "id": 380
        },
        {
            "id": 39
        },
        {
            "id": 393
        },
        {
            "id": 318
        },
        {
            "id": 297
        },
        {
            "id": 48
        },
        {
            "id": 322
        },
        {
            "id": 386
        },
        {
            "id": 376
        },
        {
            "id": 326
        },
        {
            "id": 283
        },
        {
            "id": 97
        },
        {
            "id": 244
        },
        {
            "id": 56
        },
        {
            "id": 452
        },
        {
            "id": 336
        },
        {
            "id": 372
        },
        {
            "id": 291
        },
        {
            "id": 320
        },
        {
            "id": 22
        },
        {
            "id": 242
        },
        {
            "id": 469
        },
        {
            "id": 402
        },
        {
            "id": 339
        },
        {
            "id": 295
        },
        {
            "id": 342
        },
        {
            "id": 75
        },
        {
            "id": 74
        },
        {
            "id": 158
        },
        {
            "id": 186
        },
        {
            "id": 480
        },
        {
            "id": 261
        },
        {
            "id": 225
        },
        {
            "id": 341
        },
        {
            "id": 11
        },
        {
            "id": 81
        },
        {
            "id": 355
        },
        {
            "id": 296
        },
        {
            "id": 414
        },
        {
            "id": 365
        },
        {
            "id": 455
        },
        {
            "id": 308
        },
        {
            "id": 465
        },
        {
            "id": 208
        },
        {
            "id": 47
        },
        {
            "id": 37
        },
        {
            "id": 371
        },
        {
            "id": 199
        },
        {
            "id": 289
        },
        {
            "id": 373
        },
        {
            "id": 442
        },
        {
            "id": 408
        },
        {
            "id": 367
        },
        {
            "id": 468
        },
        {
            "id": 379
        },
        {
            "id": 346
        },
        {
            "id": 475
        },
        {
            "id": 165
        },
        {
            "id": 450
        },
        {
            "id": 358
        },
        {
            "id": 394
        },
        {
            "id": 419
        },
        {
            "id": 425
        },
        {
            "id": 169
        },
        {
            "id": 321
        },
        {
            "id": 255
        },
        {
            "id": 125
        },
        {
            "id": 445
        },
        {
            "id": 460
        },
        {
            "id": 292
        },
        {
            "id": 406
        },
        {
            "id": 435
        },
        {
            "id": 157
        },
        {
            "id": 383
        },
        {
            "id": 441
        },
        {
            "id": 423
        },
        {
            "id": 77
        },
        {
            "id": 279
        },
        {
            "id": 360
        },
        {
            "id": 216
        },
        {
            "id": 424
        },
        {
            "id": 204
        },
        {
            "id": 153
        },
        {
            "id": 403
        },
        {
            "id": 454
        },
        {
            "id": 461
        },
        {
            "id": 209
        },
        {
            "id": 257
        },
        {
            "id": 129
        },
        {
            "id": 193
        },
        {
            "id": 122
        },
        {
            "id": 123
        },
        {
            "id": 259
        },
        {
            "id": 42
        },
        {
            "id": 102
        },
        {
            "id": 21
        },
        {
            "id": 415
        },
        {
            "id": 121
        },
        {
            "id": 436
        },
        {
            "id": 19
        },
        {
            "id": 79
        },
        {
            "id": 453
        },
        {
            "id": 349
        },
        {
            "id": 311
        },
        {
            "id": 370
        },
        {
            "id": 410
        },
        {
            "id": 249
        },
        {
            "id": 417
        },
        {
            "id": 351
        },
        {
            "id": 382
        },
        {
            "id": 132
        },
        {
            "id": 13
        }
    ],
    "links": [
        {
            "weight": 0.017146,
            "source": 1,
            "target": 427
        },
        {
            "weight": 0.015991,
            "source": 1,
            "target": 366
        },
        {
            "weight": 0.073842,
            "source": 1,
            "target": 135
        },
        {
            "weight": 0.002934,
            "source": 366,
            "target": 308
        },
        {
            "weight": 0.010361,
            "source": 366,
            "target": 465
        },
        {
            "weight": 0.033331,
            "source": 3,
            "target": 61
        },
        {
            "weight": 0.046394,
            "source": 3,
            "target": 112
        },
        {
            "weight": 0.009541,
            "source": 3,
            "target": 284
        },
        {
            "weight": 0.102732,
            "source": 61,
            "target": 147
        },
        {
            "weight": 0.251238,
            "source": 61,
            "target": 214
        },
        {
            "weight": 0.154945,
            "source": 112,
            "target": 57
        },
        {
            "weight": 0.024136,
            "source": 112,
            "target": 176
        },
        {
            "weight": 0.017475,
            "source": 6,
            "target": 99
        },
        {
            "weight": 0.010817,
            "source": 6,
            "target": 251
        },
        {
            "weight": 0.036864,
            "source": 6,
            "target": 231
        },
        {
            "weight": 0.059947,
            "source": 7,
            "target": 177
        },
        {
            "weight": 0.033131,
            "source": 7,
            "target": 451
        },
        {
            "weight": 0.063882,
            "source": 7,
            "target": 176
        },
        {
            "weight": 0.285752,
            "source": 8,
            "target": 27
        },
        {
            "weight": 0.009772,
            "source": 8,
            "target": 17
        },
        {
            "weight": 1e-06,
            "source": 8,
            "target": 315
        },
        {
            "weight": 0.047,
            "source": 27,
            "target": 78
        },
        {
            "weight": 0.045973,
            "source": 27,
            "target": 0
        },
        {
            "weight": 0.180674,
            "source": 17,
            "target": 428
        },
        {
            "weight": 0.031768,
            "source": 17,
            "target": 313
        },
        {
            "weight": 0.00874,
            "source": 9,
            "target": 62
        },
        {
            "weight": 0.046447,
            "source": 9,
            "target": 174
        },
        {
            "weight": 0.054839,
            "source": 9,
            "target": 171
        },
        {
            "weight": 1e-06,
            "source": 174,
            "target": 142
        },
        {
            "weight": 0.007613,
            "source": 174,
            "target": 173
        },
        {
            "weight": 0.041222,
            "source": 10,
            "target": 343
        },
        {
            "weight": 0.022683,
            "source": 10,
            "target": 426
        },
        {
            "weight": 0.077683,
            "source": 10,
            "target": 135
        },
        {
            "weight": 0.036866,
            "source": 426,
            "target": 403
        },
        {
            "weight": 0.062509,
            "source": 426,
            "target": 454
        },
        {
            "weight": 0.01408,
            "source": 14,
            "target": 474
        },
        {
            "weight": 0.003306,
            "source": 14,
            "target": 364
        },
        {
            "weight": 0.00085,
            "source": 14,
            "target": 361
        },
        {
            "weight": 0.028739,
            "source": 364,
            "target": 296
        },
        {
            "weight": 0.001703,
            "source": 364,
            "target": 414
        },
        {
            "weight": 0.001929,
            "source": 15,
            "target": 4
        },
        {
            "weight": 0.002005,
            "source": 15,
            "target": 206
        },
        {
            "weight": 0.00801,
            "source": 15,
            "target": 423
        },
        {
            "weight": 0.067552,
            "source": 313,
            "target": 203
        },
        {
            "weight": 0.046339,
            "source": 313,
            "target": 240
        },
        {
            "weight": 0.008882,
            "source": 18,
            "target": 348
        },
        {
            "weight": 0.006881,
            "source": 18,
            "target": 106
        },
        {
            "weight": 0.008036,
            "source": 18,
            "target": 399
        },
        {
            "weight": 0.016299,
            "source": 348,
            "target": 75
        },
        {
            "weight": 0.063414,
            "source": 348,
            "target": 74
        },
        {
            "weight": 0.083158,
            "source": 106,
            "target": 71
        },
        {
            "weight": 0.004537,
            "source": 106,
            "target": 273
        },
        {
            "weight": 0.005852,
            "source": 20,
            "target": 184
        },
        {
            "weight": 0.000789,
            "source": 20,
            "target": 356
        },
        {
            "weight": 1e-06,
            "source": 20,
            "target": 161
        },
        {
            "weight": 0.001602,
            "source": 356,
            "target": 480
        },
        {
            "weight": 0.003427,
            "source": 356,
            "target": 261
        },
        {
            "weight": 0.002069,
            "source": 25,
            "target": 303
        },
        {
            "weight": 1e-06,
            "source": 25,
            "target": 95
        },
        {
            "weight": 1e-06,
            "source": 25,
            "target": 305
        },
        {
            "weight": 0.017618,
            "source": 32,
            "target": 86
        },
        {
            "weight": 0.009462,
            "source": 32,
            "target": 228
        },
        {
            "weight": 0.0046,
            "source": 32,
            "target": 425
        },
        {
            "weight": 0.005932,
            "source": 228,
            "target": 317
        },
        {
            "weight": 1e-06,
            "source": 228,
            "target": 462
        },
        {
            "weight": 0.001986,
            "source": 33,
            "target": 479
        },
        {
            "weight": 0.001943,
            "source": 33,
            "target": 108
        },
        {
            "weight": 1e-06,
            "source": 33,
            "target": 65
        },
        {
            "weight": 0.029795,
            "source": 35,
            "target": 170
        },
        {
            "weight": 0.03514,
            "source": 35,
            "target": 368
        },
        {
            "weight": 0.010072,
            "source": 35,
            "target": 301
        },
        {
            "weight": 0.058472,
            "source": 368,
            "target": 208
        },
        {
            "weight": 0.007796,
            "source": 368,
            "target": 47
        },
        {
            "weight": 0.125177,
            "source": 41,
            "target": 404
        },
        {
            "weight": 0.063472,
            "source": 41,
            "target": 444
        },
        {
            "weight": 0.020041,
            "source": 41,
            "target": 191
        },
        {
            "weight": 0.075163,
            "source": 404,
            "target": 460
        },
        {
            "weight": 0.043014,
            "source": 404,
            "target": 292
        },
        {
            "weight": 0.018792,
            "source": 444,
            "target": 394
        },
        {
            "weight": 0.022122,
            "source": 444,
            "target": 262
        },
        {
            "weight": 0.035191,
            "source": 43,
            "target": 146
        },
        {
            "weight": 0.009539,
            "source": 43,
            "target": 136
        },
        {
            "weight": 0.08012,
            "source": 43,
            "target": 133
        },
        {
            "weight": 0.040529,
            "source": 146,
            "target": 390
        },
        {
            "weight": 0.043414,
            "source": 146,
            "target": 422
        },
        {
            "weight": 0.022152,
            "source": 136,
            "target": 46
        },
        {
            "weight": 0.031172,
            "source": 136,
            "target": 256
        },
        {
            "weight": 0.086914,
            "source": 45,
            "target": 29
        },
        {
            "weight": 0.027401,
            "source": 45,
            "target": 334
        },
        {
            "weight": 0.018197,
            "source": 45,
            "target": 475
        },
        {
            "weight": 0.022541,
            "source": 46,
            "target": 40
        },
        {
            "weight": 0.029626,
            "source": 46,
            "target": 85
        },
        {
            "weight": 0.00135,
            "source": 49,
            "target": 124
        },
        {
            "weight": 0.003718,
            "source": 49,
            "target": 227
        },
        {
            "weight": 0.030679,
            "source": 49,
            "target": 304
        },
        {
            "weight": 1e-06,
            "source": 124,
            "target": 293
        },
        {
            "weight": 0.000294,
            "source": 124,
            "target": 433
        },
        {
            "weight": 0.015105,
            "source": 227,
            "target": 145
        },
        {
            "weight": 0.005614,
            "source": 227,
            "target": 332
        },
        {
            "weight": 0.02929,
            "source": 50,
            "target": 221
        },
        {
            "weight": 0.003242,
            "source": 50,
            "target": 278
        },
        {
            "weight": 0.005006,
            "source": 50,
            "target": 231
        },
        {
            "weight": 0.021428,
            "source": 278,
            "target": 401
        },
        {
            "weight": 0.02662,
            "source": 278,
            "target": 374
        },
        {
            "weight": 0.019372,
            "source": 52,
            "target": 392
        },
        {
            "weight": 0.011659,
            "source": 52,
            "target": 211
        },
        {
            "weight": 0.004549,
            "source": 52,
            "target": 420
        },
        {
            "weight": 0.03515,
            "source": 53,
            "target": 247
        },
        {
            "weight": 0.009905,
            "source": 53,
            "target": 266
        },
        {
            "weight": 0.003184,
            "source": 53,
            "target": 363
        },
        {
            "weight": 0.016658,
            "source": 266,
            "target": 128
        },
        {
            "weight": 0.012468,
            "source": 266,
            "target": 92
        },
        {
            "weight": 0.052151,
            "source": 59,
            "target": 180
        },
        {
            "weight": 0.007134,
            "source": 59,
            "target": 126
        },
        {
            "weight": 1e-06,
            "source": 59,
            "target": 66
        },
        {
            "weight": 0.050948,
            "source": 59,
            "target": 273
        },
        {
            "weight": 0.010017,
            "source": 66,
            "target": 467
        },
        {
            "weight": 0.002063,
            "source": 66,
            "target": 248
        },
        {
            "weight": 0.076883,
            "source": 63,
            "target": 67
        },
        {
            "weight": 0.013555,
            "source": 63,
            "target": 463
        },
        {
            "weight": 0.031588,
            "source": 63,
            "target": 143
        },
        {
            "weight": 0.006723,
            "source": 64,
            "target": 120
        },
        {
            "weight": 0.003844,
            "source": 64,
            "target": 229
        },
        {
            "weight": 0.078466,
            "source": 64,
            "target": 464
        },
        {
            "weight": 0.004682,
            "source": 229,
            "target": 431
        },
        {
            "weight": 0.009536,
            "source": 229,
            "target": 267
        },
        {
            "weight": 0.051435,
            "source": 65,
            "target": 80
        },
        {
            "weight": 0.00472,
            "source": 65,
            "target": 423
        },
        {
            "weight": 1e-06,
            "source": 80,
            "target": 316
        },
        {
            "weight": 0.0078,
            "source": 80,
            "target": 381
        },
        {
            "weight": 1e-06,
            "source": 248,
            "target": 189
        },
        {
            "weight": 1e-06,
            "source": 248,
            "target": 150
        },
        {
            "weight": 0.031127,
            "source": 68,
            "target": 432
        },
        {
            "weight": 0.016663,
            "source": 68,
            "target": 187
        },
        {
            "weight": 0.018854,
            "source": 68,
            "target": 262
        },
        {
            "weight": 0.008966,
            "source": 432,
            "target": 209
        },
        {
            "weight": 1e-06,
            "source": 432,
            "target": 257
        },
        {
            "weight": 0.028748,
            "source": 187,
            "target": 44
        },
        {
            "weight": 0.01464,
            "source": 187,
            "target": 398
        },
        {
            "weight": 0.014158,
            "source": 69,
            "target": 230
        },
        {
            "weight": 1e-06,
            "source": 69,
            "target": 30
        },
        {
            "weight": 0.055086,
            "source": 69,
            "target": 240
        },
        {
            "weight": 0.004419,
            "source": 70,
            "target": 231
        },
        {
            "weight": 0.004333,
            "source": 70,
            "target": 387
        },
        {
            "weight": 0.002147,
            "source": 70,
            "target": 435
        },
        {
            "weight": 0.008196,
            "source": 387,
            "target": 245
        },
        {
            "weight": 0.00796,
            "source": 387,
            "target": 192
        },
        {
            "weight": 0.001395,
            "source": 72,
            "target": 207
        },
        {
            "weight": 0.002086,
            "source": 72,
            "target": 418
        },
        {
            "weight": 0.008217,
            "source": 72,
            "target": 192
        },
        {
            "weight": 0.014975,
            "source": 207,
            "target": 396
        },
        {
            "weight": 0.015106,
            "source": 207,
            "target": 232
        },
        {
            "weight": 0.014379,
            "source": 418,
            "target": 77
        },
        {
            "weight": 0.003835,
            "source": 418,
            "target": 254
        },
        {
            "weight": 1e-06,
            "source": 76,
            "target": 298
        },
        {
            "weight": 0.007835,
            "source": 76,
            "target": 269
        },
        {
            "weight": 1e-06,
            "source": 76,
            "target": 381
        },
        {
            "weight": 0.003826,
            "source": 269,
            "target": 340
        },
        {
            "weight": 1e-06,
            "source": 269,
            "target": 116
        },
        {
            "weight": 0.008304,
            "source": 381,
            "target": 475
        },
        {
            "weight": 0.146639,
            "source": 82,
            "target": 138
        },
        {
            "weight": 0.020364,
            "source": 82,
            "target": 384
        },
        {
            "weight": 0.041923,
            "source": 82,
            "target": 288
        },
        {
            "weight": 0.135937,
            "source": 384,
            "target": 165
        },
        {
            "weight": 0.126982,
            "source": 384,
            "target": 127
        },
        {
            "weight": 0.004219,
            "source": 84,
            "target": 152
        },
        {
            "weight": 0.011632,
            "source": 84,
            "target": 105
        },
        {
            "weight": 0.008843,
            "source": 84,
            "target": 254
        },
        {
            "weight": 0.00816,
            "source": 105,
            "target": 287
        },
        {
            "weight": 0.005922,
            "source": 105,
            "target": 236
        },
        {
            "weight": 0.022867,
            "source": 87,
            "target": 117
        },
        {
            "weight": 0.001845,
            "source": 87,
            "target": 101
        },
        {
            "weight": 0.00249,
            "source": 87,
            "target": 433
        },
        {
            "weight": 0.04865,
            "source": 101,
            "target": 89
        },
        {
            "weight": 0.004454,
            "source": 101,
            "target": 388
        },
        {
            "weight": 0.017114,
            "source": 91,
            "target": 197
        },
        {
            "weight": 0.004536,
            "source": 91,
            "target": 149
        },
        {
            "weight": 0.023222,
            "source": 91,
            "target": 113
        },
        {
            "weight": 0.008521,
            "source": 149,
            "target": 271
        },
        {
            "weight": 1e-06,
            "source": 149,
            "target": 350
        },
        {
            "weight": 1e-06,
            "source": 92,
            "target": 38
        },
        {
            "weight": 0.031462,
            "source": 92,
            "target": 357
        },
        {
            "weight": 0.024458,
            "source": 93,
            "target": 416
        },
        {
            "weight": 0.003861,
            "source": 93,
            "target": 233
        },
        {
            "weight": 0.007148,
            "source": 93,
            "target": 408
        },
        {
            "weight": 0.070419,
            "source": 233,
            "target": 290
        },
        {
            "weight": 0.00241,
            "source": 233,
            "target": 223
        },
        {
            "weight": 0.004925,
            "source": 94,
            "target": 181
        },
        {
            "weight": 0.009371,
            "source": 94,
            "target": 407
        },
        {
            "weight": 0.012833,
            "source": 94,
            "target": 133
        },
        {
            "weight": 0.017488,
            "source": 181,
            "target": 315
        },
        {
            "weight": 0.019849,
            "source": 181,
            "target": 151
        },
        {
            "weight": 0.00603,
            "source": 407,
            "target": 284
        },
        {
            "weight": 0.008506,
            "source": 407,
            "target": 365
        },
        {
            "weight": 0.131065,
            "source": 96,
            "target": 73
        },
        {
            "weight": 0.115909,
            "source": 96,
            "target": 166
        },
        {
            "weight": 0.146835,
            "source": 96,
            "target": 453
        },
        {
            "weight": 0.043109,
            "source": 100,
            "target": 478
        },
        {
            "weight": 1e-06,
            "source": 100,
            "target": 264
        },
        {
            "weight": 0.012711,
            "source": 100,
            "target": 369
        },
        {
            "weight": 0.017907,
            "source": 103,
            "target": 252
        },
        {
            "weight": 0.006041,
            "source": 103,
            "target": 119
        },
        {
            "weight": 0.0075,
            "source": 103,
            "target": 168
        },
        {
            "weight": 0.021828,
            "source": 252,
            "target": 440
        },
        {
            "weight": 0.028412,
            "source": 252,
            "target": 363
        },
        {
            "weight": 0.083759,
            "source": 119,
            "target": 466
        },
        {
            "weight": 0.008236,
            "source": 119,
            "target": 241
        },
        {
            "weight": 0.005402,
            "source": 104,
            "target": 200
        },
        {
            "weight": 0.014847,
            "source": 104,
            "target": 107
        },
        {
            "weight": 0.027746,
            "source": 104,
            "target": 256
        },
        {
            "weight": 0.023004,
            "source": 273,
            "target": 198
        },
        {
            "weight": 0.064505,
            "source": 109,
            "target": 54
        },
        {
            "weight": 1e-06,
            "source": 109,
            "target": 137
        },
        {
            "weight": 0.074071,
            "source": 109,
            "target": 282
        },
        {
            "weight": 0.01319,
            "source": 137,
            "target": 182
        },
        {
            "weight": 0.010316,
            "source": 137,
            "target": 457
        },
        {
            "weight": 0.020027,
            "source": 110,
            "target": 319
        },
        {
            "weight": 0.037549,
            "source": 110,
            "target": 28
        },
        {
            "weight": 0.001498,
            "source": 110,
            "target": 263
        },
        {
            "weight": 0.015682,
            "source": 176,
            "target": 409
        },
        {
            "weight": 0.011948,
            "source": 113,
            "target": 190
        },
        {
            "weight": 0.012539,
            "source": 113,
            "target": 179
        },
        {
            "weight": 0.054644,
            "source": 190,
            "target": 164
        },
        {
            "weight": 0.048177,
            "source": 190,
            "target": 217
        },
        {
            "weight": 1e-06,
            "source": 114,
            "target": 58
        },
        {
            "weight": 0.004114,
            "source": 114,
            "target": 347
        },
        {
            "weight": 1e-06,
            "source": 114,
            "target": 156
        },
        {
            "weight": 0.017043,
            "source": 115,
            "target": 239
        },
        {
            "weight": 0.025429,
            "source": 115,
            "target": 335
        },
        {
            "weight": 0.074071,
            "source": 115,
            "target": 282
        },
        {
            "weight": 0.148054,
            "source": 239,
            "target": 16
        },
        {
            "weight": 0.047902,
            "source": 239,
            "target": 222
        },
        {
            "weight": 0.002305,
            "source": 335,
            "target": 291
        },
        {
            "weight": 1e-06,
            "source": 335,
            "target": 320
        },
        {
            "weight": 1e-06,
            "source": 116,
            "target": 456
        },
        {
            "weight": 1e-06,
            "source": 116,
            "target": 345
        },
        {
            "weight": 1e-06,
            "source": 118,
            "target": 447
        },
        {
            "weight": 1e-06,
            "source": 118,
            "target": 260
        },
        {
            "weight": 0.146694,
            "source": 118,
            "target": 339
        },
        {
            "weight": 0.014305,
            "source": 241,
            "target": 218
        },
        {
            "weight": 0.021013,
            "source": 241,
            "target": 430
        },
        {
            "weight": 1e-06,
            "source": 293,
            "target": 438
        },
        {
            "weight": 0.012964,
            "source": 293,
            "target": 333
        },
        {
            "weight": 1e-06,
            "source": 433,
            "target": 129
        },
        {
            "weight": 0.01408,
            "source": 127,
            "target": 163
        },
        {
            "weight": 0.013212,
            "source": 127,
            "target": 412
        },
        {
            "weight": 0.059315,
            "source": 130,
            "target": 139
        },
        {
            "weight": 0.042693,
            "source": 130,
            "target": 168
        },
        {
            "weight": 0.02877,
            "source": 130,
            "target": 464
        },
        {
            "weight": 0.057952,
            "source": 168,
            "target": 377
        },
        {
            "weight": 0.025605,
            "source": 133,
            "target": 453
        },
        {
            "weight": 0.07803,
            "source": 134,
            "target": 36
        },
        {
            "weight": 0.037923,
            "source": 134,
            "target": 135
        },
        {
            "weight": 0.019423,
            "source": 134,
            "target": 284
        },
        {
            "weight": 0.006206,
            "source": 256,
            "target": 312
        },
        {
            "weight": 0.072915,
            "source": 182,
            "target": 175
        },
        {
            "weight": 0.017043,
            "source": 182,
            "target": 399
        },
        {
            "weight": 0.052372,
            "source": 457,
            "target": 349
        },
        {
            "weight": 0.009322,
            "source": 457,
            "target": 342
        },
        {
            "weight": 0.023400999999999998,
            "source": 457,
            "target": 453
        },
        {
            "weight": 0.019451,
            "source": 140,
            "target": 90
        },
        {
            "weight": 0.009,
            "source": 140,
            "target": 337
        },
        {
            "weight": 0.084519,
            "source": 140,
            "target": 443
        },
        {
            "weight": 0.021432,
            "source": 337,
            "target": 22
        },
        {
            "weight": 0.014926,
            "source": 337,
            "target": 242
        },
        {
            "weight": 0.015253,
            "source": 143,
            "target": 31
        },
        {
            "weight": 0.003515,
            "source": 143,
            "target": 442
        },
        {
            "weight": 0.113749,
            "source": 144,
            "target": 210
        },
        {
            "weight": 0.090655,
            "source": 144,
            "target": 88
        },
        {
            "weight": 0.023114,
            "source": 144,
            "target": 183
        },
        {
            "weight": 0.198339,
            "source": 151,
            "target": 131
        },
        {
            "weight": 0.003365,
            "source": 151,
            "target": 162
        },
        {
            "weight": 0.018294,
            "source": 162,
            "target": 411
        },
        {
            "weight": 0.014728,
            "source": 162,
            "target": 389
        },
        {
            "weight": 0.025371,
            "source": 155,
            "target": 378
        },
        {
            "weight": 1e-06,
            "source": 155,
            "target": 299
        },
        {
            "weight": 0.107105,
            "source": 155,
            "target": 389
        },
        {
            "weight": 0.035703,
            "source": 378,
            "target": 468
        },
        {
            "weight": 0.178464,
            "source": 378,
            "target": 288
        },
        {
            "weight": 0.058502,
            "source": 299,
            "target": 338
        },
        {
            "weight": 0.013166,
            "source": 299,
            "target": 309
        },
        {
            "weight": 0.002657,
            "source": 156,
            "target": 83
        },
        {
            "weight": 0.008332,
            "source": 156,
            "target": 305
        },
        {
            "weight": 0.096928,
            "source": 159,
            "target": 148
        },
        {
            "weight": 1e-06,
            "source": 159,
            "target": 369
        },
        {
            "weight": 0.012749,
            "source": 159,
            "target": 395
        },
        {
            "weight": 0.0065,
            "source": 369,
            "target": 37
        },
        {
            "weight": 0.006865,
            "source": 160,
            "target": 111
        },
        {
            "weight": 0.018949,
            "source": 160,
            "target": 205
        },
        {
            "weight": 0.03631,
            "source": 160,
            "target": 332
        },
        {
            "weight": 0.005682,
            "source": 205,
            "target": 276
        },
        {
            "weight": 0.008786,
            "source": 205,
            "target": 324
        },
        {
            "weight": 0.001939,
            "source": 161,
            "target": 51
        },
        {
            "weight": 0.007904,
            "source": 161,
            "target": 274
        },
        {
            "weight": 0.040562,
            "source": 411,
            "target": 441
        },
        {
            "weight": 0.046264,
            "source": 411,
            "target": 171
        },
        {
            "weight": 0.044065,
            "source": 389,
            "target": 188
        },
        {
            "weight": 1e-06,
            "source": 167,
            "target": 253
        },
        {
            "weight": 1e-06,
            "source": 167,
            "target": 314
        },
        {
            "weight": 0.018907,
            "source": 167,
            "target": 352
        },
        {
            "weight": 0.001995,
            "source": 314,
            "target": 380
        },
        {
            "weight": 1e-06,
            "source": 314,
            "target": 39
        },
        {
            "weight": 0.012448,
            "source": 377,
            "target": 367
        },
        {
            "weight": 0.04528,
            "source": 377,
            "target": 219
        },
        {
            "weight": 0.030332,
            "source": 171,
            "target": 202
        },
        {
            "weight": 0.134416,
            "source": 202,
            "target": 265
        },
        {
            "weight": 0.01501,
            "source": 202,
            "target": 470
        },
        {
            "weight": 0.108123,
            "source": 409,
            "target": 157
        },
        {
            "weight": 0.1002,
            "source": 409,
            "target": 383
        },
        {
            "weight": 0.035055,
            "source": 178,
            "target": 405
        },
        {
            "weight": 0.034897,
            "source": 178,
            "target": 185
        },
        {
            "weight": 0.008104,
            "source": 178,
            "target": 218
        },
        {
            "weight": 0.033811,
            "source": 185,
            "target": 24
        },
        {
            "weight": 0.004929,
            "source": 185,
            "target": 439
        },
        {
            "weight": 0.020037,
            "source": 179,
            "target": 458
        },
        {
            "weight": 0.007339,
            "source": 179,
            "target": 324
        },
        {
            "weight": 0.040501,
            "source": 315,
            "target": 393
        },
        {
            "weight": 0.038499,
            "source": 399,
            "target": 255
        },
        {
            "weight": 0.100519,
            "source": 183,
            "target": 258
        },
        {
            "weight": 0.050041,
            "source": 183,
            "target": 472
        },
        {
            "weight": 1e-06,
            "source": 439,
            "target": 122
        },
        {
            "weight": 0.002036,
            "source": 439,
            "target": 123
        },
        {
            "weight": 0.00399,
            "source": 398,
            "target": 169
        },
        {
            "weight": 0.02018,
            "source": 398,
            "target": 321
        },
        {
            "weight": 0.089701,
            "source": 188,
            "target": 446
        },
        {
            "weight": 0.013535,
            "source": 188,
            "target": 437
        },
        {
            "weight": 0.010354,
            "source": 446,
            "target": 436
        },
        {
            "weight": 0.00309,
            "source": 446,
            "target": 19
        },
        {
            "weight": 0.045059,
            "source": 437,
            "target": 322
        },
        {
            "weight": 0.013857,
            "source": 437,
            "target": 194
        },
        {
            "weight": 0.012878,
            "source": 217,
            "target": 421
        },
        {
            "weight": 0.026585,
            "source": 217,
            "target": 354
        },
        {
            "weight": 0.00879,
            "source": 191,
            "target": 464
        },
        {
            "weight": 0.005275,
            "source": 191,
            "target": 365
        },
        {
            "weight": 0.016558,
            "source": 192,
            "target": 281
        },
        {
            "weight": 0.036706,
            "source": 194,
            "target": 391
        },
        {
            "weight": 0.195596,
            "source": 194,
            "target": 359
        },
        {
            "weight": 0.013534,
            "source": 359,
            "target": 225
        },
        {
            "weight": 0.016283,
            "source": 359,
            "target": 224
        },
        {
            "weight": 0.008377,
            "source": 195,
            "target": 459
        },
        {
            "weight": 0.001594,
            "source": 195,
            "target": 329
        },
        {
            "weight": 0.01609,
            "source": 195,
            "target": 215
        },
        {
            "weight": 0.00447,
            "source": 329,
            "target": 244
        },
        {
            "weight": 0.020771,
            "source": 329,
            "target": 56
        },
        {
            "weight": 0.022723,
            "source": 196,
            "target": 272
        },
        {
            "weight": 0.058296,
            "source": 196,
            "target": 280
        },
        {
            "weight": 0.021101,
            "source": 196,
            "target": 277
        },
        {
            "weight": 0.014411,
            "source": 280,
            "target": 306
        },
        {
            "weight": 0.010557,
            "source": 280,
            "target": 286
        },
        {
            "weight": 0.023149,
            "source": 470,
            "target": 417
        },
        {
            "weight": 0.185207,
            "source": 470,
            "target": 351
        },
        {
            "weight": 0.010229,
            "source": 324,
            "target": 376
        },
        {
            "weight": 0.001839,
            "source": 232,
            "target": 413
        },
        {
            "weight": 0.004181,
            "source": 232,
            "target": 5
        },
        {
            "weight": 0.044772,
            "source": 212,
            "target": 270
        },
        {
            "weight": 0.01192,
            "source": 212,
            "target": 477
        },
        {
            "weight": 0.014403,
            "source": 212,
            "target": 322
        },
        {
            "weight": 0.039169,
            "source": 213,
            "target": 23
        },
        {
            "weight": 0.017318,
            "source": 213,
            "target": 277
        },
        {
            "weight": 0.034041,
            "source": 213,
            "target": 471
        },
        {
            "weight": 0.052178,
            "source": 277,
            "target": 12
        },
        {
            "weight": 1e-06,
            "source": 215,
            "target": 234
        },
        {
            "weight": 0.004916,
            "source": 215,
            "target": 267
        },
        {
            "weight": 0.003811,
            "source": 234,
            "target": 352
        },
        {
            "weight": 0.063803,
            "source": 234,
            "target": 300
        },
        {
            "weight": 0.074996,
            "source": 354,
            "target": 158
        },
        {
            "weight": 0.004847,
            "source": 354,
            "target": 186
        },
        {
            "weight": 0.01274,
            "source": 218,
            "target": 397
        },
        {
            "weight": 0.00695,
            "source": 219,
            "target": 201
        },
        {
            "weight": 0.009831,
            "source": 219,
            "target": 243
        },
        {
            "weight": 0.028036,
            "source": 223,
            "target": 141
        },
        {
            "weight": 0.019307,
            "source": 223,
            "target": 328
        },
        {
            "weight": 1e-06,
            "source": 224,
            "target": 60
        },
        {
            "weight": 1e-06,
            "source": 224,
            "target": 327
        },
        {
            "weight": 0.013839,
            "source": 332,
            "target": 452
        },
        {
            "weight": 0.006212,
            "source": 462,
            "target": 311
        },
        {
            "weight": 0.02111,
            "source": 462,
            "target": 370
        },
        {
            "weight": 1e-06,
            "source": 267,
            "target": 473
        },
        {
            "weight": 0.003097,
            "source": 290,
            "target": 400
        },
        {
            "weight": 0.033645,
            "source": 290,
            "target": 220
        },
        {
            "weight": 0.003738,
            "source": 352,
            "target": 326
        },
        {
            "weight": 0.016026,
            "source": 300,
            "target": 385
        },
        {
            "weight": 0.00147,
            "source": 300,
            "target": 237
        },
        {
            "weight": 0.011933,
            "source": 235,
            "target": 26
        },
        {
            "weight": 0.00217,
            "source": 235,
            "target": 448
        },
        {
            "weight": 0.001966,
            "source": 235,
            "target": 294
        },
        {
            "weight": 0.011745,
            "source": 448,
            "target": 79
        },
        {
            "weight": 0.007899,
            "source": 448,
            "target": 310
        },
        {
            "weight": 0.014507,
            "source": 237,
            "target": 325
        },
        {
            "weight": 1e-06,
            "source": 237,
            "target": 307
        },
        {
            "weight": 1e-06,
            "source": 307,
            "target": 55
        },
        {
            "weight": 0.00629,
            "source": 307,
            "target": 305
        },
        {
            "weight": 0.005886,
            "source": 238,
            "target": 471
        },
        {
            "weight": 0.029812,
            "source": 238,
            "target": 361
        },
        {
            "weight": 0.011621,
            "source": 238,
            "target": 268
        },
        {
            "weight": 0.008012,
            "source": 471,
            "target": 301
        },
        {
            "weight": 0.008753,
            "source": 361,
            "target": 341
        },
        {
            "weight": 0.129018,
            "source": 240,
            "target": 395
        },
        {
            "weight": 0.139585,
            "source": 395,
            "target": 371
        },
        {
            "weight": 0.04551,
            "source": 430,
            "target": 461
        },
        {
            "weight": 0.01957,
            "source": 430,
            "target": 263
        },
        {
            "weight": 0.006136,
            "source": 245,
            "target": 172
        },
        {
            "weight": 0.008156,
            "source": 245,
            "target": 2
        },
        {
            "weight": 0.040712,
            "source": 440,
            "target": 259
        },
        {
            "weight": 0.020169,
            "source": 440,
            "target": 42
        },
        {
            "weight": 0.04708,
            "source": 363,
            "target": 355
        },
        {
            "weight": 0.014451,
            "source": 254,
            "target": 154
        },
        {
            "weight": 0.022903,
            "source": 312,
            "target": 476
        },
        {
            "weight": 0.087595,
            "source": 312,
            "target": 449
        },
        {
            "weight": 0.02044,
            "source": 262,
            "target": 294
        },
        {
            "weight": 0.035756,
            "source": 294,
            "target": 226
        },
        {
            "weight": 0.006681,
            "source": 263,
            "target": 362
        },
        {
            "weight": 0.044488,
            "source": 362,
            "target": 11
        },
        {
            "weight": 0.024074,
            "source": 362,
            "target": 81
        },
        {
            "weight": 0.04108,
            "source": 473,
            "target": 382
        },
        {
            "weight": 0.012452,
            "source": 473,
            "target": 132
        },
        {
            "weight": 0.000958,
            "source": 268,
            "target": 434
        },
        {
            "weight": 0.003434,
            "source": 268,
            "target": 342
        },
        {
            "weight": 0.025604,
            "source": 434,
            "target": 424
        },
        {
            "weight": 0.022495,
            "source": 434,
            "target": 406
        },
        {
            "weight": 0.018483,
            "source": 274,
            "target": 331
        },
        {
            "weight": 0.001873,
            "source": 274,
            "target": 414
        },
        {
            "weight": 0.121382,
            "source": 275,
            "target": 98
        },
        {
            "weight": 0.088541,
            "source": 275,
            "target": 34
        },
        {
            "weight": 0.037533,
            "source": 275,
            "target": 472
        },
        {
            "weight": 0.085445,
            "source": 285,
            "target": 429
        },
        {
            "weight": 0.016779,
            "source": 285,
            "target": 472
        },
        {
            "weight": 0.011632,
            "source": 285,
            "target": 443
        },
        {
            "weight": 0.109389,
            "source": 288,
            "target": 375
        },
        {
            "weight": 1e-06,
            "source": 333,
            "target": 336
        },
        {
            "weight": 0.010326,
            "source": 333,
            "target": 372
        },
        {
            "weight": 0.107454,
            "source": 338,
            "target": 469
        },
        {
            "weight": 0.024514,
            "source": 338,
            "target": 402
        },
        {
            "weight": 0.151908,
            "source": 309,
            "target": 353
        },
        {
            "weight": 0.021025,
            "source": 309,
            "target": 443
        },
        {
            "weight": 0.079383,
            "source": 301,
            "target": 330
        },
        {
            "weight": 0.051833,
            "source": 302,
            "target": 323
        },
        {
            "weight": 0.023279,
            "source": 302,
            "target": 420
        },
        {
            "weight": 0.026211,
            "source": 302,
            "target": 342
        },
        {
            "weight": 0.036027,
            "source": 420,
            "target": 216
        },
        {
            "weight": 0.048978,
            "source": 304,
            "target": 344
        },
        {
            "weight": 0.031371,
            "source": 304,
            "target": 406
        },
        {
            "weight": 0.038583,
            "source": 310,
            "target": 246
        },
        {
            "weight": 0.009837,
            "source": 310,
            "target": 250
        },
        {
            "weight": 0.124071,
            "source": 393,
            "target": 450
        },
        {
            "weight": 0.122687,
            "source": 393,
            "target": 358
        },
        {
            "weight": 0.031785,
            "source": 318,
            "target": 297
        },
        {
            "weight": 0.025125,
            "source": 318,
            "target": 48
        },
        {
            "weight": 0.0221,
            "source": 318,
            "target": 424
        },
        {
            "weight": 0.04461,
            "source": 322,
            "target": 386
        },
        {
            "weight": 0.010063,
            "source": 326,
            "target": 283
        },
        {
            "weight": 0.001807,
            "source": 326,
            "target": 97
        },
        {
            "weight": 0.039125,
            "source": 402,
            "target": 125
        },
        {
            "weight": 0.047851,
            "source": 402,
            "target": 445
        },
        {
            "weight": 0.21825,
            "source": 339,
            "target": 295
        },
        {
            "weight": 0.044142,
            "source": 339,
            "target": 441
        },
        {
            "weight": 0.003291,
            "source": 414,
            "target": 423
        },
        {
            "weight": 0.155369,
            "source": 365,
            "target": 455
        },
        {
            "weight": 0.010062,
            "source": 371,
            "target": 199
        },
        {
            "weight": 1e-06,
            "source": 371,
            "target": 289
        },
        {
            "weight": 0.030732,
            "source": 373,
            "target": 442
        },
        {
            "weight": 0.018214,
            "source": 373,
            "target": 408
        },
        {
            "weight": 0.015933,
            "source": 373,
            "target": 379
        },
        {
            "weight": 0.035064,
            "source": 442,
            "target": 21
        },
        {
            "weight": 0.001817,
            "source": 408,
            "target": 435
        },
        {
            "weight": 0.298337,
            "source": 468,
            "target": 410
        },
        {
            "weight": 0.132374,
            "source": 468,
            "target": 249
        },
        {
            "weight": 0.014069,
            "source": 379,
            "target": 346
        },
        {
            "weight": 0.074976,
            "source": 379,
            "target": 406
        },
        {
            "weight": 0.023337,
            "source": 475,
            "target": 13
        },
        {
            "weight": 0.034366,
            "source": 394,
            "target": 419
        },
        {
            "weight": 0.006934,
            "source": 394,
            "target": 425
        },
        {
            "weight": 0.001992,
            "source": 419,
            "target": 279
        },
        {
            "weight": 0.006805,
            "source": 419,
            "target": 360
        },
        {
            "weight": 0.014973,
            "source": 425,
            "target": 153
        },
        {
            "weight": 0.011153,
            "source": 445,
            "target": 415
        },
        {
            "weight": 0.03216,
            "source": 445,
            "target": 121
        },
        {
            "weight": 0.031753,
            "source": 435,
            "target": 193
        },
        {
            "weight": 0.172489,
            "source": 441,
            "target": 102
        },
        {
            "weight": 0.034146,
            "source": 424,
            "target": 204
        }
    ]
}